tzhutils/__init__.py
tzhutils/utils.py
tzhutils-0.0.1.dist-info/LICENSE
tzhutils-0.0.1.dist-info/METADATA
tzhutils-0.0.1.dist-info/WHEEL
tzhutils-0.0.1.dist-info/top_level.txt
tzhutils-0.0.1.dist-info/RECORD
