Metadata-Version: 2.1
Name: tzhutils
Version: 0.0.1
Summary: A small utils for decorator package
Home-page: https://github.com/664956016/tzhutils.git
Author: tzh
Author-email: 13060820957@163.com
License: UNKNOWN
Platform: UNKNOWN
Classifier: Programming Language :: Python :: 3
Classifier: License :: OSI Approved :: MIT License
Classifier: Operating System :: OS Independent
Requires-Dist: progressbar
